airflow/providers/filemaker/__init__.py
airflow/providers/filemaker/auth/__init__.py
airflow/providers/filemaker/auth/cognitoauth.py
airflow/providers/filemaker/example_dags/example_filemaker.py
airflow/providers/filemaker/example_dags/example_filemaker_request_data.py
airflow/providers/filemaker/example_dags/example_filemaker_to_s3.py
airflow/providers/filemaker/executors/__init__.py
airflow/providers/filemaker/hooks/__init__.py
airflow/providers/filemaker/hooks/connection.py
airflow/providers/filemaker/hooks/filemaker.py
airflow/providers/filemaker/notifications/__init__.py
airflow/providers/filemaker/operators/__init__.py
airflow/providers/filemaker/operators/filemaker.py
airflow/providers/filemaker/sensors/__init__.py
airflow/providers/filemaker/sensors/filemaker.py
airflow/providers/filemaker/transfers/__init__.py
airflow/providers/filemaker/triggers/__init__.py
arktci_airflow_provider_filemaker-2.4.2.dist-info/METADATA
arktci_airflow_provider_filemaker-2.4.2.dist-info/WHEEL
arktci_airflow_provider_filemaker-2.4.2.dist-info/entry_points.txt
arktci_airflow_provider_filemaker-2.4.2.dist-info/top_level.txt
arktci_airflow_provider_filemaker-2.4.2.dist-info/RECORD
