Metadata-Version: 2.2
Name: arktci-airflow-provider-filemaker
Version: 2.4.2
Summary: Apache Airflow provider for FileMaker Cloud
Author-email: "Josh Lipton @ ArkTCI" <josh@arktci.com>
License: Apache License 2.0
Project-URL: Homepage, https://github.com/ArkTCI/airflow-providers
Classifier: Programming Language :: Python :: 3
Classifier: License :: OSI Approved :: Apache Software License
Classifier: Operating System :: OS Independent
Requires-Python: >=3.8
Requires-Dist: apache-airflow>=2.0.0
Requires-Dist: boto3>=1.16.0
Requires-Dist: requests>=2.25.0
Requires-Dist: pandas>=1.0.0
Requires-Dist: pycognito>=2023.01.0
